CHANGELOG.txt
LICENSE.txt
MANIFEST.in
README.txt
ez_setup.py
setup.cfg
setup.py
example/README.txt
example/app.yaml
example/development.ini
example/gae.ini
example/pyxer.ini
example/public/__init__.py
example/public/favicon.ico
example/public/index.html
example/public/layout.html
example/public/master.css
example/public/master.html
example/public/robots.txt
example/public/directory/README-GAE.txt
example/public/directory/README.txt
example/public/directory/__init__.py
example/public/directory/index.html
example/public/directory/show.html
example/public/error/README-GAE.txt
example/public/error/README.txt
example/public/error/__init__.py
example/public/error/index.html
example/public/guestbook/README-GAE.txt
example/public/guestbook/README.txt
example/public/guestbook/__init__.py
example/public/guestbook/index.html
example/public/guestbook/model.py
example/public/json/README-GAE.txt
example/public/json/README.txt
example/public/json/__init__.py
example/public/json/index.html
example/public/session/README-GAE.txt
example/public/session/README.txt
example/public/session/__init__.py
example/public/session/index.html
example/public/wiki/README.txt
example/public/wiki/__init__.py
example/public/wiki/index.html
example/public/wiki/model.py
src/pyxer/__init__.py
src/pyxer/app.py
src/pyxer/base.py
src/pyxer/command.py
src/pyxer/controller.py
src/pyxer/create.py
src/pyxer/helpers.py
src/pyxer/routing.py
src/pyxer.egg-info/PKG-INFO
src/pyxer.egg-info/SOURCES.txt
src/pyxer.egg-info/dependency_links.txt
src/pyxer.egg-info/entry_points.txt
src/pyxer.egg-info/top_level.txt
src/pyxer/gae/__init__.py
src/pyxer/paster/__init__.py
src/pyxer/recaptcha/__init__.py
src/pyxer/sling/__init__.py
src/pyxer/sling/sling.py
src/pyxer/template/__init__.py
src/pyxer/template/cssselect.py
src/pyxer/template/templatestream.py
src/pyxer/template/genshi/__init__.py
src/pyxer/template/genshi/builder.py
src/pyxer/template/genshi/core.py
src/pyxer/template/genshi/input.py
src/pyxer/template/genshi/output.py
src/pyxer/template/genshi/path.py
src/pyxer/template/genshi/util.py
src/pyxer/template/genshi/filters/__init__.py
src/pyxer/template/genshi/filters/html.py
