Metadata-Version: 1.0
Name: pyxer
Version: 0.7.1
Summary: Simple Python Framework and Templating for Paste, Google App Engine (GAE) and WSGI.
Home-page: http://code.google.com/p/pyxer/
Author: Dirk Holtwick
Author-email: dirk.holtwick@gmail.com
License: MIT
Download-URL: http://pypi.python.org/pypi/pyxer
Keywords: Framework,Google App Engine,GAE,appengine,Paster,Server,Templating,Sling,Jackrabbit,JCR
Platform: UNKNOWN
